MANIFEST.in
README.rst
setup.py
danutils/__init__.py
danutils/gl.py
danutils/ostools.py
danutils/rainbow.py
danutils/reflect.py
danutils.egg-info/PKG-INFO
danutils.egg-info/SOURCES.txt
danutils.egg-info/dependency_links.txt
danutils.egg-info/top_level.txt
danutils/cuda/__init__.py
danutils/cuda/autoprep.py
danutils/cuda/autoprep_example.py
danutils/cuda/cudafunc.py
danutils/cuda/datatools.py
danutils/cuda/modtools.py
danutils/do/__init__.py
danutils/do/cleanup.py
danutils/do/interact.py
danutils/do/test.py
danutils/img/__init__.py
danutils/img/imgtools.py
danutils/lib/__init__.py
danutils/lib/getlib.py
danutils/misc/__init__.py
danutils/misc/coroutine.py
danutils/misc/debugAbort.py
danutils/misc/fastcomp.py
danutils/misc/listtools.py
danutils/misc/misctools.py
danutils/misc/ranges.py
danutils/misc/speech.py
danutils/misc/trackball.py
danutils/pandatools/__init__.py
danutils/pandatools/key_watcher.py
danutils/sci/__init__.py
danutils/sci/debugprint.py
danutils/sci/mappedarrayset.py
danutils/sci/numpytools.py
danutils/sci/setup_sci.py
danutils/sci/vis.py
danutils/wx/__init__.py
danutils/wx/staticImage.py
danutils/wx/trackballCanvas.py
danutils/wx/wxtools.py