Metadata-Version: 1.0
Name: danutils
Version: 0.0.0
Summary: UNKNOWN
Home-page: UNKNOWN
Author: UNKNOWN
Author-email: UNKNOWN
License: BSD
Platform: UNKNOWN
